odoo8_addon_sale_triple_discount-8.0.1.0.0.99.dev5-py3.8-nspkg.pth
odoo_addons/sale_triple_discount/README.rst
odoo_addons/sale_triple_discount/__init__.py
odoo_addons/sale_triple_discount/__openerp__.py
odoo_addons/sale_triple_discount/i18n/ca.po
odoo_addons/sale_triple_discount/i18n/de.po
odoo_addons/sale_triple_discount/i18n/es.po
odoo_addons/sale_triple_discount/i18n/es_VE.po
odoo_addons/sale_triple_discount/i18n/fr.po
odoo_addons/sale_triple_discount/i18n/hr.po
odoo_addons/sale_triple_discount/i18n/it.po
odoo_addons/sale_triple_discount/i18n/nl_NL.po
odoo_addons/sale_triple_discount/i18n/pt_BR.po
odoo_addons/sale_triple_discount/i18n/ro.po
odoo_addons/sale_triple_discount/i18n/sale_triple_discount.pot
odoo_addons/sale_triple_discount/i18n/sl.po
odoo_addons/sale_triple_discount/i18n/tr.po
odoo_addons/sale_triple_discount/i18n/tr_TR.po
odoo_addons/sale_triple_discount/models/__init__.py
odoo_addons/sale_triple_discount/models/sale_order.py
odoo_addons/sale_triple_discount/models/sale_order_line.py
odoo_addons/sale_triple_discount/models/stock_move.py
odoo_addons/sale_triple_discount/readme/CONFIGURE.rst
odoo_addons/sale_triple_discount/readme/CONTRIBUTORS.rst
odoo_addons/sale_triple_discount/readme/DESCRIPTION.rst
odoo_addons/sale_triple_discount/readme/USAGE.rst
odoo_addons/sale_triple_discount/static/description/icon.png
odoo_addons/sale_triple_discount/static/description/index.html
odoo_addons/sale_triple_discount/tests/__init__.py
odoo_addons/sale_triple_discount/tests/test_sale_triple_discount.py
odoo_addons/sale_triple_discount/views/sale_order_view.xml
odoo8_addon_sale_triple_discount-8.0.1.0.0.99.dev5.dist-info/METADATA
odoo8_addon_sale_triple_discount-8.0.1.0.0.99.dev5.dist-info/WHEEL
odoo8_addon_sale_triple_discount-8.0.1.0.0.99.dev5.dist-info/namespace_packages.txt
odoo8_addon_sale_triple_discount-8.0.1.0.0.99.dev5.dist-info/top_level.txt
odoo8_addon_sale_triple_discount-8.0.1.0.0.99.dev5.dist-info/RECORD
